{
    "domains": {
        "default": {
            "records": {
                "host1": {
                    "A": {
                        "name": "host1.flux",
                        "address": "192.168.10.60"
                    }
                },
                "ha1": {
                    "A": {
                        "name":  "flux",
                        "address": "192.168.10.60"
                    }
                },
                "operator": {
                    "CNAME": {
                        "name": "flux-operator",
                        "target": "flux.alwaldend.com."
                    }
                }
            }
        }
    }
}
