{
    "id": 1166558069,
    "status_display": "Accepted",
    "lang": "python3",
    "question_id": 387,
    "title_slug": "first-unique-character-in-a-string",
    "code": "class Solution:\n    def firstUniqChar(self, s: str) -\u003e int:\n        counter = [0] * 26\n\n        for char in s:\n            idx = ord(char) - ord('a')\n            if counter[idx] in (0, 1):\n                counter[idx] += 1\n        for i in range(len(s)):\n            if counter[ord(s[i]) - ord('a')] == 1:\n                return i\n        return -1",
    "title": "First Unique Character in a String",
    "url": "/submissions/detail/1166558069/",
    "lang_name": "Python3",
    "time": "1 year, 3 months",
    "timestamp": 1707117178,
    "status": 10,
    "runtime": "103 ms",
    "is_pending": "Not Pending",
    "memory": "16.7 MB",
    "compare_result": "111111111111111111111111111111111111111111111111111111111111111111111111111111111111111111111111111111111",
    "flag_type": 1
}